py_weather_cli/__init__.py
py_weather_cli/ascii_art.py
py_weather_cli/main.py
py_weather_cli/openweathermap.py
py_weather_cli/utils.py
py_weather_cli/weather.py
py_weather_cli-1.0.2.dist-info/LICENSE
py_weather_cli-1.0.2.dist-info/METADATA
py_weather_cli-1.0.2.dist-info/WHEEL
py_weather_cli-1.0.2.dist-info/entry_points.txt
py_weather_cli-1.0.2.dist-info/top_level.txt
py_weather_cli-1.0.2.dist-info/RECORD
