Metadata-Version: 2.1
Name: py-weather-cli
Version: 1.0.2
Summary: python version implementation of `wego` which is a weather forecast client for the terminal.
Home-page: https://github.com/faris-shi/py_weather_cli
Author: Faris Shi
Author-email: faris.shi84@gmail.com
License: MIT
Keywords: wego-python weather english cli forecast ascii-art
Platform: UNKNOWN
Classifier: Development Status :: 4 - Beta
Classifier: Environment :: Console
Classifier: License :: OSI Approved :: MIT License
Classifier: Intended Audience :: Developers
Classifier: Natural Language :: English
Classifier: Topic :: Utilities
Classifier: Operating System :: OS Independent
Classifier: Programming Language :: Python :: 3.3
Classifier: Programming Language :: Python :: 3.4
Classifier: Programming Language :: Python :: 3.5
Classifier: Programming Language :: Python :: 3.6
Classifier: Programming Language :: Python :: 3.7
Classifier: Programming Language :: Python :: 3.8
Requires-Dist: requests
Requires-Dist: click
